midas_store/__init__.py
midas_store/meta.py
midas_store/module.py
midas_store/simulator.py
midas_store-2.0.1.dist-info/licenses/LICENSE
midas_store-2.0.1.dist-info/METADATA
midas_store-2.0.1.dist-info/WHEEL
midas_store-2.0.1.dist-info/top_level.txt
midas_store-2.0.1.dist-info/RECORD
