Metadata-Version: 2.4
Name: midas-store
Version: 2.0.1
Summary: A database simulator that stores every input.
Author-email: Stephan Balduin <stephan.balduin@offis.de>
Project-URL: Documentation, https://midas-mosaik.gitlab.io/midas
Requires-Python: >=3.8
License-File: LICENSE
Requires-Dist: midas-mosaik~=2.0.0
Requires-Dist: mosaik_api
Requires-Dist: pandas
Requires-Dist: tables
Dynamic: license-file
